proxy6/__init__.py
proxy6/api.py
proxy6/errors.py
proxy6/schemas.py
proxy6/types.py
proxysix-1.0.0a4.dist-info/LICENSE
proxysix-1.0.0a4.dist-info/WHEEL
proxysix-1.0.0a4.dist-info/METADATA
proxysix-1.0.0a4.dist-info/RECORD
